[
  {
    "name": "Двойная петля",
    "category": "Фильмы",
    "video": "https://ab3-762-405gv.stream-balancer-allo-1.live/M2/65/1/1765434057/mTkCaQ_M_dLihhVEbajk_w/5/1080/1/967785/master.m3u8",
    "info": {
      "plot": "Два пилота американских ВМС во время Корейской войны становятся близкими друзьями и братьями по оружию. Во время очередного задания одного из лётчиков подбивают аккурат над вражеской территорией. Командование не видит необходимости в спасательной операции, но истинная преданность не позволит солдату оставить товарища в беде...\n\nВ ролях: Джонатан Мейджорс, Глен Пауэлл, Christina Jackson, Томас Садоски, Daren Kagasoff, Джо Джонас, Spencer Neville, Nick Hargrove, Бун Платт, Dean Denton\nРежиссёр(ы): Дж. Д. Диллард\nОригинал: Devotion\n16+  •  2022  •  United States of America  •  138 мин.\nTMDb 7.1; TMDb ID: 653851\nЖанр: военный, драма, боевик\nПремьера: 2022-11-23\nСтудия: Black Label Media",
      "poster": "https://image.tmdb.org/t/p/w500/mr7oPaFMOw2mNOJGxBc6c6t6QCr.jpg",
      "backdrop": "https://image.tmdb.org/t/p/original/tY36rkGlREg5m9CaguckR8jZCye.jpg",
      "bg": "https://image.tmdb.org/t/p/original/tY36rkGlREg5m9CaguckR8jZCye.jpg",
      "year": 2022,
      "rating": "TMDb 7.1",
      "duration": 8280,
      "cast": [
        "Джонатан Мейджорс",
        "Глен Пауэлл",
        "Christina Jackson",
        "Томас Садоски",
        "Daren Kagasoff",
        "Джо Джонас",
        "Spencer Neville",
        "Nick Hargrove",
        "Бун Платт",
        "Dean Denton"
      ],
      "director": [
        "Дж. Д. Диллард"
      ],
      "country": [
        "United States of America"
      ],
      "genre": [
        "военный",
        "драма",
        "боевик"
      ],
      "studio": "Black Label Media"
    },
    "headers": {
      "User-Agent": "Mozilla/5.0 (Windows NT 10.0; Win64; x64) AppleWebKit/537.36 (KHTML, like Gecko) Chrome/143.0.0.0 Safari/537.36 Edg/143.0.0.0",
      "Referer": "https://tech-as.allarknow.online/?token_movie=48543ec0aa0df6ff9d15a3dbda6fea&token=44d582eb68d934c529538eb8a191df",
      "Origin": "https://tech-as.allarknow.online"
    }
  }
]
